LICENSE
MANIFEST.in
README.rst
setup.cfg
setup.py
versioneer.py
tests/__init__.py
tests/test_general.py
tpDcc/__init__.py
tpDcc/config/__init__.py
tpDcc/config/__version__.py
tpDcc/config/_version.py
tpDcc/config/development/tpDcc-core.yml
tpDcc/config/development/tpDcc-interface.yml
tpDcc/config/development/tpDcc-libs-curves.yml
tpDcc/config/development/tpDcc-libs.datalibrary.yml
tpDcc/config/development/tpDcc-naming.yml
tpDcc/config/development/tpDcc-tools-datalibrary.yml
tpDcc/config/development/tpDcc-tools-nameit.yml
tpDcc/config/development/tpDcc-tools-renamer.yml
tpDcc/config/development/tpDcc-tools.yml
tpDcc/config/development/maya/tpDcc-naming.yml
tpDcc/config/development/maya/tpDcc-tools-renamer.yml
tpDcc/config/production/tpDcc-core.yml
tpDcc/config/production/tpDcc-interface.yml
tpDcc/config/production/tpDcc-libs-curves.yml
tpDcc/config/production/tpDcc-libs-datalibrary.yml
tpDcc/config/production/tpDcc-naming.yml
tpDcc/config/production/tpDcc-tools-datalibrary.yml
tpDcc/config/production/tpDcc-tools-nameit.yml
tpDcc/config/production/tpDcc-tools-renamer.yml
tpDcc/config/production/tpDcc-tools.yml
tpDcc/config/production/maya/tpDcc-naming.yml
tpDcc/config/production/maya/tpDcc-tools-renamer.yml
tpDcc_config.egg-info/PKG-INFO
tpDcc_config.egg-info/SOURCES.txt
tpDcc_config.egg-info/dependency_links.txt
tpDcc_config.egg-info/not-zip-safe
tpDcc_config.egg-info/requires.txt
tpDcc_config.egg-info/top_level.txt