Metadata-Version: 2.1
Name: tpDcc-config
Version: 0.0.9
Summary: tpDcc module that contains configuration files
Home-page: https://github.com/tpDcc/tpDcc-config
Author: Tomas Poveda
Author-email: tpovedatd@gmail.com
License: MIT
Platform: UNKNOWN
Provides-Extra: dev
Provides-Extra: test
